<?xml version="1.0" encoding="utf-8"?>
<!DOCTYPE hibernate-mapping PUBLIC "-//Hibernate/Hibernate Mapping DTD 3.0//EN"
"http://www.hibernate.org/dtd/hibernate-mapping-3.0.dtd">
<!-- 
    Mapping file autogenerated by MyEclipse Persistence Tools
-->
<hibernate-mapping>
    <class name="com.world.wen.model.AwsWeiboMsg" table="aws_weibo_msg" catalog="iask">
        <id name="id" type="java.lang.Long">
            <column name="id" />
            <generator class="native" />
        </id>
        <property name="createdAt" type="java.lang.Integer">
            <column name="created_at" not-null="true" />
        </property>
        <property name="msgAuthorUid" type="java.lang.Long">
            <column name="msg_author_uid" not-null="true" />
        </property>
        <property name="text" type="java.lang.String">
            <column name="text" not-null="true" />
        </property>
        <property name="accessKey" type="java.lang.String">
            <column name="access_key" length="32" not-null="true" />
        </property>
        <property name="hasAttach" type="java.lang.Boolean">
            <column name="has_attach" not-null="true" />
        </property>
        <property name="uid" type="java.lang.Integer">
            <column name="uid" not-null="true" />
        </property>
        <property name="weiboUid" type="java.lang.Long">
            <column name="weibo_uid" not-null="true" />
        </property>
        <property name="questionId" type="java.lang.Integer">
            <column name="question_id" />
        </property>
        <property name="ticketId" type="java.lang.Integer">
            <column name="ticket_id" />
        </property>
    </class>
</hibernate-mapping>
